{"cameraMode":{"drawMode":0,"name":"Shaded","section":"Shading Mode"},"sceneLighting":true,"audioPlay":false,"sceneViewState":{"showFog":true,"showMaterialUpdate":false,"showSkybox":true,"showFlares":true,"showImageEffects":true,"showParticleSystems":true,"showVisualEffectGraphs":true,"m_FxEnabled":true},"in2DMode":false,"pivot":{"x":6.592148780822754,"y":-0.5758928656578064,"z":0.7448546886444092},"rotation":{"x":-0.41338321566581728,"y":-0.3734883666038513,"z":0.1910470426082611,"w":-0.8081737756729126},"size":14.049001693725586,"orthographic":false}